{"cameraMode":{"drawMode":0,"name":"Shaded","section":"Shading Mode"},"sceneLighting":false,"audioPlay":false,"sceneViewState":{"m_AlwaysRefresh":false,"showFog":true,"showSkybox":false,"showFlares":true,"showImageEffects":true,"showParticleSystems":true,"showVisualEffectGraphs":true,"m_FxEnabled":true},"in2DMode":false,"pivot":{"x":-0.5382846593856812,"y":0.9694082736968994,"z":0.04312849044799805},"rotation":{"x":0.20439653098583222,"y":-0.24938137829303742,"z":0.053936515003442767,"w":0.9450522661209106},"size":1.4877972602844239,"orthographic":false}